{"@class":"Animation","id":{"uuid":"A3542A42-5FE1-4930-A8E9-D4AB9BE5780B"},"tracks":[{"@class":"Vector3BehaviorTrack","clips":[{"@class":"Vector3BehaviorClip","beginTime":0,"duration":2500,"script":"Vector3ValueBehaviorClipScript","behavior":{"@class":"Vector3PlainBehavior","times":[0,2500],"values":[-6.543902486555453e-8,0.2730594575405121,-0.06856662780046463,-6.543902486555453e-8,0.2730594575405121,-0.06856662780046463]}}],"script":"Vector3BehaviorTrackScript","accessor":"PositionBlendAccessor"},{"@class":"QuaternionBehaviorTrack","clips":[{"@class":"QuaternionBehaviorClip","beginTime":0,"duration":2500,"script":"QuaternionValueBehaviorClipScript","behavior":{"@class":"QuaternionPlainBehavior","times":[0,2500],"values":[-0.18819744884967805,-1.1707940217320356e-7,2.0191382077427989e-7,0.9821312427520752,-0.18819744884967805,-1.1707940217320356e-7,2.0191382077427989e-7,0.9821312427520752]}}],"script":"QuaternionBehaviorTrackScript","accessor":"RotationQBlendAccessor"},{"@class":"Vector3BehaviorTrack","clips":[{"@class":"Vector3BehaviorClip","beginTime":0,"duration":2500,"script":"Vector3ValueBehaviorClipScript","behavior":{"@class":"Vector3PlainBehavior","times":[0,2500],"values":[1.0,0.9999999403953552,0.9999999403953552,1.0,0.9999999403953552,0.9999999403953552]}}],"script":"Vector3BehaviorTrackScript","accessor":"ScaleBlendAccessor"}]}