{"@class":"Animation","id":{"uuid":"BCC21B0C-D9BF-472A-95BF-8A2B181334F4"},"tracks":[{"@class":"Vector3BehaviorTrack","clips":[{"@class":"Vector3BehaviorClip","beginTime":0,"duration":6666,"script":"Vector3ValueBehaviorClipScript","behavior":{"@class":"Vector3PlainBehavior","times":[0,6666],"values":[1.9308613374846574e-8,-0.08752994239330292,-0.220864936709404,1.9308613374846574e-8,-0.08752994239330292,-0.220864936709404]}}],"script":"Vector3BehaviorTrackScript","accessor":"PositionBlendAccessor"},{"@class":"QuaternionBehaviorTrack","clips":[{"@class":"QuaternionBehaviorClip","beginTime":0,"duration":6666,"script":"QuaternionValueBehaviorClipScript","behavior":{"@class":"QuaternionPlainBehavior","times":[0,6666],"values":[0.8977611064910889,-1.925423731563569e-8,3.924264291299551e-8,0.4404827058315277,0.8977611064910889,-1.925423731563569e-8,3.924264291299551e-8,0.4404827058315277]}}],"script":"QuaternionBehaviorTrackScript","accessor":"RotationQBlendAccessor"},{"@class":"Vector3BehaviorTrack","clips":[{"@class":"Vector3BehaviorClip","beginTime":0,"duration":6666,"script":"Vector3ValueBehaviorClipScript","behavior":{"@class":"Vector3PlainBehavior","times":[0,6666],"values":[1.0,1.0,1.0,1.0,1.0,1.0]}}],"script":"Vector3BehaviorTrackScript","accessor":"ScaleBlendAccessor"}]}