{"@class":"Animation","id":{"uuid":"CB136385-4E1C-4DE0-BBA2-B63DAC944BF9"},"tracks":[{"@class":"Vector3BehaviorTrack","clips":[{"@class":"Vector3BehaviorClip","beginTime":0,"duration":3999,"script":"Vector3ValueBehaviorClipScript","behavior":{"@class":"Vector3PlainBehavior","times":[0,3999],"values":[-1.900480128824711e-8,0.053766220808029178,1.1641532182693482e-9,-1.900480128824711e-8,0.053766220808029178,1.1641532182693482e-9]}}],"script":"Vector3BehaviorTrackScript","accessor":"PositionBlendAccessor"},{"@class":"QuaternionBehaviorTrack","clips":[{"@class":"QuaternionBehaviorClip","beginTime":0,"duration":3999,"script":"QuaternionValueBehaviorClipScript","behavior":{"@class":"QuaternionPlainBehavior","times":[0,3999],"values":[-0.044036220759153369,0.0009958952432498336,0.021731847897171975,0.9987930655479431,-0.044036220759153369,0.0009958952432498336,0.021731847897171975,0.9987930655479431]}}],"script":"QuaternionBehaviorTrackScript","accessor":"RotationQBlendAccessor"},{"@class":"Vector3BehaviorTrack","clips":[{"@class":"Vector3BehaviorClip","beginTime":0,"duration":3999,"script":"Vector3ValueBehaviorClipScript","behavior":{"@class":"Vector3PlainBehavior","times":[0,3999],"values":[0.9999999403953552,1.0000001192092896,1.0,0.9999999403953552,1.0000001192092896,1.0]}}],"script":"Vector3BehaviorTrackScript","accessor":"ScaleBlendAccessor"}]}