{"@class":"TimeLineScript","id":{"uuid":"A28CFE10-5AE6-4623-B104-23D10B236F9E"},"name":"Animation","enableOnAwake":false,"loop":false,"jumpToFirstFrameAtEnd":false,"speed":1.0,"weight":1.0,"loopStartTime":0,"loopDuration":0,"is_imported":false,"type":"user","scripts":{"@class":"StdListRuntimeScript","list":[{"@class":"AnimationScript","id":{"uuid":"7121DC7B-44AA-4C50-A724-9A7E750526B5"},"name":"Capsule","enableOnAwake":false,"OwnerLink":{"@class":"BindingLink","targetId":{"uuid":"DC86261B-9DDB-409C-ABEC-2866D0BACD87"},"targetRelativeAddress":{"@class":"NodeRelativeAddressBase","index":0,"name":"Wooden Barrel 2"}},"animation":{"uuid":"E7DE7114-5F12-41E4-A46A-CBC7FFADC0FE"},"AnimationType":"object3D","is_imported":false,"isEnabled":true},{"@class":"AnimationScript","id":{"uuid":"34D82E0D-5136-4DDF-909A-2907EA49E8AA"},"name":"Box_side_F","enableOnAwake":false,"OwnerLink":{"@class":"BindingLink","targetId":{"uuid":"7BC36784-2405-44B4-AF7E-5C2C1E7B7B89"},"targetRelativeAddress":{"@class":"NodeRelativeAddressBase","index":0,"name":"Wooden Barrel 2","subaddress":{"@class":"NodeRelativeAddressBase","index":0,"name":"Group","subaddress":{"@class":"NodeRelativeAddressBase","index":0,"name":"Cylinder.003"}}}},"animation":{"uuid":"591A6FA8-F518-43DA-8716-3DC7BBF6D5C6"},"AnimationType":"object3D","is_imported":false,"isEnabled":true},{"@class":"AnimationScript","id":{"uuid":"ADAB28D0-7181-4140-A9C3-B0589E55B1BD"},"name":"Box_side_L","enableOnAwake":false,"OwnerLink":{"@class":"BindingLink","targetId":{"uuid":"ED39E682-5955-4D47-9402-B4E4C2892400"},"targetRelativeAddress":{"@class":"NodeRelativeAddressBase","index":0,"name":"Wooden Barrel 2","subaddress":{"@class":"NodeRelativeAddressBase","index":1,"name":"Cylinder.004"}}},"animation":{"uuid":"85BAE580-0827-4249-95C5-106CAAF99BE8"},"AnimationType":"object3D","is_imported":false,"isEnabled":true},{"@class":"AnimationScript","id":{"uuid":"499B6B70-98EC-497D-A1DF-62CE43B7A5FA"},"name":"Box_side_B","enableOnAwake":false,"OwnerLink":{"@class":"BindingLink","targetId":{"uuid":"3F841BB6-554F-4CEE-A8D8-7A6B291DAD24"},"targetRelativeAddress":{"@class":"NodeRelativeAddressBase","index":0,"name":"Wooden Barrel 2","subaddress":{"@class":"NodeRelativeAddressBase","index":2,"name":"Cylinder.005"}}},"animation":{"uuid":"D17597BF-BB1A-47EB-A1BA-9979415EBA00"},"AnimationType":"object3D","is_imported":false,"isEnabled":true},{"@class":"AnimationScript","id":{"uuid":"5F720BBE-12E0-4EC4-95BA-ED9DD1F5D51B"},"name":"Box_side_R","enableOnAwake":false,"OwnerLink":{"@class":"BindingLink","targetId":{"uuid":"8B8C764E-B340-4083-AA60-9DEE60BB4A2E"},"targetRelativeAddress":{"@class":"NodeRelativeAddressBase","index":0,"name":"Wooden Barrel 2","subaddress":{"@class":"NodeRelativeAddressBase","index":3,"name":"Group","subaddress":{"@class":"NodeRelativeAddressBase","index":0,"name":"Cylinder.006"}}}},"animation":{"uuid":"67DF2BCB-CC71-4915-9040-A10084E3D0F0"},"AnimationType":"object3D","is_imported":false,"isEnabled":true},{"@class":"AnimationScript","id":{"uuid":"7AD45BDE-F4A8-447B-B274-C368DDE18A76"},"name":"Cylinder.007","enableOnAwake":false,"OwnerLink":{"@class":"BindingLink","targetId":{"uuid":"791D8E4A-48EA-402B-8026-CEF9D9563E00"},"targetRelativeAddress":{"@class":"NodeRelativeAddressBase","index":0,"name":"Wooden Barrel 2","subaddress":{"@class":"NodeRelativeAddressBase","index":4,"name":"Cylinder.007"}}},"animation":{"uuid":"68C6E0FE-72BB-4927-9C4C-D9EF8F919E61"},"AnimationType":"object3D","is_imported":false,"isEnabled":true},{"@class":"AnimationScript","id":{"uuid":"5359940F-BCC7-4790-A6CC-612E0BCB9773"},"name":"Cylinder.008","enableOnAwake":false,"OwnerLink":{"@class":"BindingLink","targetId":{"uuid":"3F954EAF-2050-48B8-9C27-DF10A0767DB3"},"targetRelativeAddress":{"@class":"NodeRelativeAddressBase","index":0,"name":"Wooden Barrel 2","subaddress":{"@class":"NodeRelativeAddressBase","index":5,"name":"Cylinder.008"}}},"animation":{"uuid":"058193D3-18F0-4B03-804A-96F74E378156"},"AnimationType":"object3D","is_imported":false,"isEnabled":true},{"@class":"AnimationScript","id":{"uuid":"D3CF41E0-5AB5-4C2C-9D69-EE4C27479406"},"name":"Cylinder.012","enableOnAwake":false,"OwnerLink":{"@class":"BindingLink","targetId":{"uuid":"5C853371-B2A4-4F93-8D8B-0414D382874B"},"targetRelativeAddress":{"@class":"NodeRelativeAddressBase","index":0,"name":"Wooden Barrel 2","subaddress":{"@class":"NodeRelativeAddressBase","index":12,"name":"Cylinder.012"}}},"animation":{"uuid":"84E2467E-B2CE-4AF1-9EE3-E96161A51990"},"AnimationType":"object3D","is_imported":false,"isEnabled":true},{"@class":"AnimationScript","id":{"uuid":"D2CE4CFD-5BC4-4774-A6F6-E3D2856F6B7A"},"name":"Cylinder.013","enableOnAwake":false,"OwnerLink":{"@class":"BindingLink","targetId":{"uuid":"5C1A7AA6-34A4-4485-9187-27591EC24589"},"targetRelativeAddress":{"@class":"NodeRelativeAddressBase","index":0,"name":"Wooden Barrel 2","subaddress":{"@class":"NodeRelativeAddressBase","index":13,"name":"Cylinder.013"}}},"animation":{"uuid":"E45982CA-1A13-4570-8825-8714866BC9EA"},"AnimationType":"object3D","is_imported":false,"isEnabled":true},{"@class":"AnimationScript","id":{"uuid":"CE632393-E8BA-4018-815C-EFE68C8AD0FA"},"name":"Cylinder.014","enableOnAwake":false,"OwnerLink":{"@class":"BindingLink","targetId":{"uuid":"4FBC22C6-6F6F-4C40-9305-DAFD6D6D447A"},"targetRelativeAddress":{"@class":"NodeRelativeAddressBase","index":0,"name":"Wooden Barrel 2","subaddress":{"@class":"NodeRelativeAddressBase","index":14,"name":"Cylinder.014"}}},"animation":{"uuid":"82BBF44B-8834-4701-B96C-2B5F6551BA7B"},"AnimationType":"object3D","is_imported":false,"isEnabled":true},{"@class":"AnimationScript","id":{"uuid":"2BFF7D7F-C16C-4A14-B336-BDC829D62C5B"},"name":"Cylinder.015","enableOnAwake":false,"OwnerLink":{"@class":"BindingLink","targetId":{"uuid":"44067AD7-6DF8-4BB4-9471-43ADAD929B3C"},"targetRelativeAddress":{"@class":"NodeRelativeAddressBase","index":0,"name":"Wooden Barrel 2","subaddress":{"@class":"NodeRelativeAddressBase","index":15,"name":"Group","subaddress":{"@class":"NodeRelativeAddressBase","index":0,"name":"Cylinder.015"}}}},"animation":{"uuid":"FAF63D64-AB18-498A-B1B2-AC4358389A86"},"AnimationType":"object3D","is_imported":false,"isEnabled":true},{"@class":"AnimationScript","id":{"uuid":"F9A23E8D-B067-40A4-A6FE-038CAEB43BD8"},"name":"Cylinder.016","enableOnAwake":false,"OwnerLink":{"@class":"BindingLink","targetId":{"uuid":"4AE716BA-E220-47E2-A4B6-6265E1ED9E15"},"targetRelativeAddress":{"@class":"NodeRelativeAddressBase","index":0,"name":"Wooden Barrel 2","subaddress":{"@class":"NodeRelativeAddressBase","index":16,"name":"Cylinder.016"}}},"animation":{"uuid":"851D4B7F-681A-4229-929D-DB785D9C06A2"},"AnimationType":"object3D","is_imported":false,"isEnabled":true},{"@class":"AnimationScript","id":{"uuid":"CF85BDB9-8E5D-4FF3-9637-9DC9E97BB4B1"},"name":"Cylinder.017","enableOnAwake":false,"OwnerLink":{"@class":"BindingLink","targetId":{"uuid":"F5B92143-3931-4145-9369-2B31AB76025A"},"targetRelativeAddress":{"@class":"NodeRelativeAddressBase","index":0,"name":"Wooden Barrel 2","subaddress":{"@class":"NodeRelativeAddressBase","index":17,"name":"Cylinder.017"}}},"animation":{"uuid":"6A1404F9-1999-49AA-8634-8F1401055432"},"AnimationType":"object3D","is_imported":false,"isEnabled":true},{"@class":"AnimationScript","id":{"uuid":"3CB2A046-1E6B-4D5B-9252-73D0AC6ECC87"},"name":"Box_cap","enableOnAwake":false,"OwnerLink":{"@class":"BindingLink","targetId":{"uuid":"F8DCAF68-B862-4538-8E6C-5E3E0B663479"},"targetRelativeAddress":{"@class":"NodeRelativeAddressBase","index":0,"name":"Wooden Barrel 2","subaddress":{"@class":"NodeRelativeAddressBase","index":6,"name":"Cylinder.009"}}},"animation":{"uuid":"089CBAFA-4A47-4ADA-9F54-C942CB5DB856"},"AnimationType":"object3D","is_imported":false,"isEnabled":true},{"@class":"AnimationScript","id":{"uuid":"F67A7468-9A9C-4FD3-96A6-EC00062EEEAD"},"name":"Box_bottom","enableOnAwake":false,"OwnerLink":{"@class":"BindingLink","targetId":{"uuid":"CB8701AB-7526-45E4-A120-CAA7D4AE179F"},"targetRelativeAddress":{"@class":"NodeRelativeAddressBase","index":0,"name":"Wooden Barrel 2","subaddress":{"@class":"NodeRelativeAddressBase","index":9,"name":"Cylinder.018"}}},"animation":{"uuid":"3950D71E-D959-44AB-B1C0-B16CFF00B05E"},"AnimationType":"object3D","is_imported":false,"isEnabled":true},{"@class":"AnimationScript","id":{"uuid":"1298C66D-999B-436F-9E35-3487D1C16DDD"},"name":"Cylinder.010","enableOnAwake":false,"OwnerLink":{"@class":"BindingLink","targetId":{"uuid":"B388024B-3012-4524-AB0B-DE180F0C08D8"},"targetRelativeAddress":{"@class":"NodeRelativeAddressBase","index":0,"name":"Wooden Barrel 2","subaddress":{"@class":"NodeRelativeAddressBase","index":7,"name":"Cylinder.010"}}},"animation":{"uuid":"1CB2DBC7-928F-4AD9-810D-EA50073273A8"},"AnimationType":"object3D","is_imported":false,"isEnabled":true},{"@class":"AnimationScript","id":{"uuid":"352F7E29-BC60-4D89-AA13-80A8F8604844"},"name":"Cylinder.011","enableOnAwake":false,"OwnerLink":{"@class":"BindingLink","targetId":{"uuid":"BE4A4917-8488-46C3-877A-0548EBD2D622"},"targetRelativeAddress":{"@class":"NodeRelativeAddressBase","index":0,"name":"Wooden Barrel 2","subaddress":{"@class":"NodeRelativeAddressBase","index":8,"name":"Cylinder.011"}}},"animation":{"uuid":"0A7AE727-4BE6-4B90-9546-1D6BC3446D20"},"AnimationType":"object3D","is_imported":false,"isEnabled":true},{"@class":"AnimationScript","id":{"uuid":"40848B3B-96DB-4D7A-9B27-F1D3E0E48E80"},"name":"Cylinder.019","enableOnAwake":false,"OwnerLink":{"@class":"BindingLink","targetId":{"uuid":"5776426D-BB4F-4D43-905F-4AE50C2A2025"},"targetRelativeAddress":{"@class":"NodeRelativeAddressBase","index":0,"name":"Wooden Barrel 2","subaddress":{"@class":"NodeRelativeAddressBase","index":10,"name":"Cylinder.019"}}},"animation":{"uuid":"BD7271D7-749E-4EF7-9F06-BFA084486C9D"},"AnimationType":"object3D","is_imported":false,"isEnabled":true},{"@class":"AnimationScript","id":{"uuid":"97BC0E5B-13EB-422D-AB09-B91512963371"},"name":"Cylinder.020","enableOnAwake":false,"OwnerLink":{"@class":"BindingLink","targetId":{"uuid":"B8273012-D726-4901-AE7A-96E759761F20"},"targetRelativeAddress":{"@class":"NodeRelativeAddressBase","index":0,"name":"Wooden Barrel 2","subaddress":{"@class":"NodeRelativeAddressBase","index":11,"name":"Cylinder.020"}}},"animation":{"uuid":"F86368EC-68E7-4479-A515-C1B36CA3467A"},"AnimationType":"object3D","is_imported":false,"isEnabled":true},{"@class":"AnimationScript","id":{"uuid":"CB61AD8D-01F9-4755-8D55-F5FA801E5EF2"},"name":"Destructor","enableOnAwake":false,"OwnerLink":{"@class":"BindingLink","targetId":{"uuid":"A4C2D295-4F95-4170-88BA-0C57616D0C31"},"targetRelativeAddress":{"@class":"NodeRelativeAddressBase","index":0,"name":"Wooden Barrel 2","subaddress":{"@class":"NodeRelativeAddressBase","index":19,"name":"Destructor"}}},"animation":{"uuid":"2D3208F0-039F-4175-A72F-FD63CD3751BE"},"AnimationType":"object3D","is_imported":false,"isEnabled":false}]},"triggers":[{"@class":"CollisionTrigger","id":{"uuid":"6B1D09EB-890F-4427-AECD-F4028F4C6360"},"ownerScriptId":{"uuid":"A28CFE10-5AE6-4623-B104-23D10B236F9E"},"logicOperation":0,"resultType":0,"isInverted":false,"eventType":"in","targetBindingLink":{"@class":"BindingLink","targetId":{"uuid":"DC86261B-9DDB-409C-ABEC-2866D0BACD87"}},"zoneBindingLink":{"@class":"BindingLink","targetId":{"uuid":"55C5AC19-FFAF-4B09-B4A7-7E3C9DDD9334"}}},{"@class":"CollisionTrigger","id":{"uuid":"8B425F24-0FAA-4366-8B6E-7BDEE41DDCED"},"ownerScriptId":{"uuid":"A28CFE10-5AE6-4623-B104-23D10B236F9E"},"logicOperation":0,"resultType":0,"isInverted":false,"eventType":"in","targetBindingLink":{"@class":"BindingLink","targetId":{"uuid":"DC86261B-9DDB-409C-ABEC-2866D0BACD87"}},"zoneBindingLink":{"@class":"BindingLink","targetId":{"uuid":"0BE0E226-A735-4E4C-A1E1-482D86AD2438"}}},{"@class":"CollisionTrigger","id":{"uuid":"19AF34DE-86B9-4171-B159-78F8FA6CB6BC"},"ownerScriptId":{"uuid":"A28CFE10-5AE6-4623-B104-23D10B236F9E"},"logicOperation":0,"resultType":0,"isInverted":false,"eventType":"in","targetBindingLink":{"@class":"BindingLink","targetId":{"uuid":"DC86261B-9DDB-409C-ABEC-2866D0BACD87"}},"zoneBindingLink":{"@class":"BindingLink","targetId":{"uuid":"0D61A8FA-EE58-4718-8568-AA823FBBF5B5"}}},{"@class":"AnimationTrigger","id":{"uuid":"4416BA4A-51E5-4764-A692-B0759A44151B"},"ownerScriptId":{"uuid":"A28CFE10-5AE6-4623-B104-23D10B236F9E"},"logicOperation":0,"resultType":0,"isInverted":false,"event":3,"bindingLink":{"@class":"BindingLink","targetId":{"uuid":"7F0060AC-A803-4B68-9875-F30276593F88"}}}]}