{"@class":"Material","id":{"uuid":"870E1183-F38B-49C8-B197-32FFB0732D3F"},"name":"GP_Rock3_seamless","renderingType":"opaque","blendingType":"normal","detailType":"none","lightningType":"perPixel","colorsType":"no","shadingType":"pbr","sideType":"front","depthType":"default","ambient":{"values":[0.0,0.0,0.0]},"diffuse":{"values":[1.0,1.0,1.0]},"specular":{"values":[0.2224937379360199,0.2050594538450241,0.17233169078826905]},"emissive":{"values":[0.0,0.0,0.0]},"rimColor":{"values":[1.0,1.0,1.0]},"opacity":1.0,"shininess":0.40495866537094118,"metalness":0.0,"roughness":1.0,"refraction":0.5,"rimIntensity":1.0,"bloomThreshold":0.800000011920929,"normalScale":1.0,"heightScale":1.0,"diffuseMap":{"uuid":"3673BB39-1A09-4E9D-899D-246347E2E955"},"normalMap":{"uuid":"5B6C2222-D349-4B16-AB9E-16E55F2D0918"},"specularMap":{"uuid":"00000000-0000-0000-0000-000000000003"},"emissiveMap":{"uuid":"00000000-0000-0000-0000-000000000006"},"heightMap":{"uuid":"00000000-0000-0000-0000-000000000004"},"alphaMap":{"uuid":"00000000-0000-0000-0000-000000000001"},"occlusionMap":{"uuid":"00000000-0000-0000-0000-000000000005"},"roughnessMap":{"uuid":"00000000-0000-0000-0000-000000000008"},"metalnessMap":{"uuid":"00000000-0000-0000-0000-000000000007"},"envMap":{"uuid":"00000000-0000-0000-0000-000000000009"},"irrEnvMap":{"uuid":"00000000-0000-0000-0000-000000000010"},"cubemapSize":256,"cubemapUpdateSpeed":-1,"tilingOffset":{"values":[1.0,1.0,0.0,0.0]},"toonGlare":{"values":[1.0,1.0,1.0]},"toonGradient":{"@class":"StdListVector3","list":[{"values":[0.25,0.25,0.25]},{"values":[0.6000000238418579,0.6000000238418579,0.6000000238418579]},{"values":[1.0,1.0,1.0]}]}}